pytest_tuberia/__init__.py
pytest_tuberia/fixtures.py
pytest_tuberia/utils.py
tuberia/__init__.py
tuberia/__main__.py
tuberia/base_settings.py
tuberia/deployer.py
tuberia/deployer_databricks.py
tuberia/docs.py
tuberia/expectation.py
tuberia/flow.py
tuberia/settings.py
tuberia/spark.py
tuberia/table.py
tuberia/typing.py
tuberia/utils.py
tuberia/version.py
tuberia/visualization.py
tuberia-0.0.1.dist-info/entry_points.txt
tuberia-0.0.1.dist-info/WHEEL
tuberia-0.0.1.dist-info/METADATA
tuberia-0.0.1.dist-info/RECORD
