Metadata-Version: 2.1
Name: tuberia
Version: 0.0.1
Summary: Tuberia... when data engineering meets software engineering
Home-page: https://github.com/aidictive/tuberia
Keywords: pipeline,data,engineering,databricks,spark,pyspark,tables
Author: guiferviz
Author-email: guiferviz@gmail.com
Requires-Python: >=3.8,<4.0
Classifier: Programming Language :: Python :: 3
Classifier: Programming Language :: Python :: 3.8
Classifier: Programming Language :: Python :: 3.9
Classifier: Programming Language :: Python :: 3.10
Classifier: Programming Language :: Python :: 3.10
Classifier: Programming Language :: Python :: 3.8
Classifier: Programming Language :: Python :: 3.9
Classifier: Topic :: Software Development :: Libraries :: Python Modules
Provides-Extra: pyspark
Requires-Dist: delta-spark (==2.1.0); extra == "pyspark"
Requires-Dist: inflection (>=0.5.1,<0.6.0)
Requires-Dist: loguru (>=0.6.0,<0.7.0)
Requires-Dist: makefun (>=1.14.0,<2.0.0)
Requires-Dist: prefect (>=1.2.0,<2.0.0)
Requires-Dist: pydantic (>=1.9.0,<2.0.0)
Requires-Dist: pyspark (==3.3.0); extra == "pyspark"
Requires-Dist: typer (>=0.4.0,<0.5.0)
Project-URL: Documentation, https://aidictive.com/tuberia
Project-URL: Repository, https://github.com/aidictive/tuberia
